{
    "name": "customer_db",
    "profile": "tabular-data-package",
    "resources": [
        {
            "name": "balance",
            "schema": "schemas/balance.json",
            "path": "data/balance.csv",
            "control": {
                "newline": ""
            },
            "encoding": "utf-8",
            "dialect": {
                "commentChar": "#"
            },
            "profile": "tabular-data-resource",
            "scheme": "file",
            "format": "csv",
            "hashing": "md5",
            "compression": "no",
            "compressionPath": "",
            "query": {}
        },
        {
            "name": "user_id",
            "schema": "schemas/user_id.json",
            "path": "data/user_id.csv",
            "control": {
                "newline": ""
            },
            "encoding": "utf-8",
            "dialect": {
                "commentChar": "#"
            },
            "profile": "tabular-data-resource",
            "scheme": "file",
            "format": "csv",
            "hashing": "md5",
            "compression": "no",
            "compressionPath": "",
            "query": {}
        }
    ]
}
